voxelmap/__init__.py
voxelmap/core.py
voxelmap/io.py
voxelmap/mesh/__init__.py
voxelmap/mesh/image.py
voxelmap/mesh/meshgen.py
voxelmap/mesh/render.py
voxelmap-5.1.1.dist-info/licenses/LICENSE
voxelmap-5.1.1.dist-info/METADATA
voxelmap-5.1.1.dist-info/WHEEL
voxelmap-5.1.1.dist-info/top_level.txt
voxelmap-5.1.1.dist-info/RECORD
