Metadata-Version: 2.4
Name: voxelmap
Version: 5.1.1
Summary: A Python library for voxel modeling from NumPy arrays
Author-email: "Andrew R. Garcia" <garcia.gtr@gmail.com>
License: MIT
Requires-Python: >=3.8
License-File: LICENSE
Requires-Dist: numpy>=1.24.1
Requires-Dist: matplotlib>=3.6.2
Provides-Extra: io
Requires-Dist: pandas>=2.1; extra == "io"
Provides-Extra: mesh
Requires-Dist: pyvista>=0.44; extra == "mesh"
Requires-Dist: scikit-image>=0.22; extra == "mesh"
Requires-Dist: opencv-python>=4.8; extra == "mesh"
Requires-Dist: scipy>=1.11; extra == "mesh"
Provides-Extra: all
Requires-Dist: pandas>=2.1; extra == "all"
Requires-Dist: pyvista>=0.44; extra == "all"
Requires-Dist: scikit-image>=0.22; extra == "all"
Requires-Dist: opencv-python>=4.8; extra == "all"
Requires-Dist: scipy>=1.11; extra == "all"
Dynamic: license-file
